LICENSE
MANIFEST.in
README.rst
setup.py
django_model_changes/__init__.py
django_model_changes/changes.py
django_model_changes/signals.py
django_model_changes/__pycache__/__init__.cpython-36.pyc
django_model_changes/__pycache__/changes.cpython-36.pyc
django_model_changes/__pycache__/signals.cpython-36.pyc
django_model_changes_py3.egg-info/PKG-INFO
django_model_changes_py3.egg-info/SOURCES.txt
django_model_changes_py3.egg-info/dependency_links.txt
django_model_changes_py3.egg-info/top_level.txt
django_model_changes_py3.egg-info/zip-safe
docs/Makefile
docs/source/conf.py
docs/source/django_model_changes.rst
docs/source/index.rst