Metadata-Version: 1.1
Name: django-model-changes-py3
Version: 0.15.1
Summary: django-model-changes allows you to track model instance changes.
Home-page: http://github.com/iansprice/django-model-changes-py3
Author: Ian Price
Author-email: iprice@thermaline.com
License: MIT License
Platform: UNKNOWN
Classifier: Environment :: Web Environment
Classifier: Framework :: Django
Classifier: Intended Audience :: Developers
Classifier: License :: OSI Approved :: MIT License
Classifier: Operating System :: OS Independent
Classifier: Programming Language :: Python
Classifier: Programming Language :: Python :: 3
Classifier: Programming Language :: Python :: 3.6
Classifier: Topic :: Internet :: WWW/HTTP
Classifier: Topic :: Internet :: WWW/HTTP :: Dynamic Content
